{
  "themes": [
    {
      "name": "Gingerbread Man",
      "path": "Gingerbread Man",
      "works": [
        {
          "name": "Gingerbread Man 1",
          "path": "Gingerbread Man 1",
          "modified": "2025-11-21"
        },
        {
          "name": "Gingerbread Man 2",
          "path": "Gingerbread Man 2",
          "modified": "2025-11-21"
        }
      ]
    },
    {
      "name": "School Bear",
      "path": "School Bear",
      "works": [
        {
          "name": "Bear_on_Bus",
          "path": "Bear_on_Bus",
          "modified": "2025-11-21"
        },
        {
          "name": "Cooking_Bear",
          "path": "Cooking_Bear",
          "modified": "2025-11-21"
        }
      ]
    }
  ]
}